Click7XZhongwenWendang/README.md
Click7XZhongwenWendang/__init__.py
Click7XZhongwenWendang/__main__.py
Click7XZhongwenWendang/file.epub
Click7XZhongwenWendang/index.html
Click7XZhongwenWendang/css/__init__.py
Click7XZhongwenWendang/css/annotations.css
Click7XZhongwenWendang/css/main.css
Click7XZhongwenWendang/css/normalize.css
Click7XZhongwenWendang/css/popup.css
Click7XZhongwenWendang/font/__init__.py
Click7XZhongwenWendang/font/fontello.eot
Click7XZhongwenWendang/font/fontello.svg
Click7XZhongwenWendang/font/fontello.ttf
Click7XZhongwenWendang/font/fontello.woff
Click7XZhongwenWendang/img/__init__.py
Click7XZhongwenWendang/img/annotator-glyph-sprite.png
Click7XZhongwenWendang/img/annotator-icon-sprite.png
Click7XZhongwenWendang/img/apple-touch-icon.png
Click7XZhongwenWendang/img/cancelfullscreen.png
Click7XZhongwenWendang/img/close.png
Click7XZhongwenWendang/img/fullscreen.png
Click7XZhongwenWendang/img/loader.gif
Click7XZhongwenWendang/img/menu-icon.png
Click7XZhongwenWendang/img/save.png
Click7XZhongwenWendang/img/saved.png
Click7XZhongwenWendang/img/settings-s.png
Click7XZhongwenWendang/img/settings.png
Click7XZhongwenWendang/img/star.png
Click7XZhongwenWendang/js/__init__.py
Click7XZhongwenWendang/js/epub.js
Click7XZhongwenWendang/js/epub.min.js
Click7XZhongwenWendang/js/epub.min.map
Click7XZhongwenWendang/js/hooks.min.js
Click7XZhongwenWendang/js/hooks.min.map
Click7XZhongwenWendang/js/reader.js
Click7XZhongwenWendang/js/reader.js.map
Click7XZhongwenWendang/js/reader.min.js
Click7XZhongwenWendang/js/reader.min.map
Click7XZhongwenWendang/js/hooks/__init__.py
Click7XZhongwenWendang/js/hooks/extensions/__init__.py
Click7XZhongwenWendang/js/hooks/extensions/highlight.js
Click7XZhongwenWendang/js/libs/__init__.py
Click7XZhongwenWendang/js/libs/jquery.min.js
Click7XZhongwenWendang/js/libs/localforage.min.js
Click7XZhongwenWendang/js/libs/screenfull.js
Click7XZhongwenWendang/js/libs/screenfull.min.js
Click7XZhongwenWendang/js/libs/zip.min.js
click_7_x_zhongwen_wendang-2024.3.5.0.dist-info/METADATA
click_7_x_zhongwen_wendang-2024.3.5.0.dist-info/WHEEL
click_7_x_zhongwen_wendang-2024.3.5.0.dist-info/entry_points.txt
click_7_x_zhongwen_wendang-2024.3.5.0.dist-info/top_level.txt
click_7_x_zhongwen_wendang-2024.3.5.0.dist-info/RECORD
